ini/__init__.py
ini.py-0.0.5.dist-info/LICENSE
ini.py-0.0.5.dist-info/METADATA
ini.py-0.0.5.dist-info/WHEEL
ini.py-0.0.5.dist-info/top_level.txt
ini.py-0.0.5.dist-info/RECORD
