Metadata-Version: 2.1
Name: ini.py
Version: 0.0.5
Summary: a lightweight ini parser
Home-page: https://github.com/husseinraed/ini.py
Author: Hussein Raed
Author-email: me@husseinraed.cf
License: UNKNOWN
Platform: UNKNOWN
Classifier: Programming Language :: Python :: 3
Classifier: License :: OSI Approved :: MIT License
Classifier: Operating System :: OS Independent
Requires-Python: >=3.6
